{
  "required": true,
  "minVersion": "0.8",
  "package": "com.evandev.spicedcider.mixin",
  "plugin": "com.evandev.spicedcider.mixin.SpicedCiderMixinPlugin",
  "compatibilityLevel": "JAVA_21",
  "mixins": [
    "cookscollection.CooksCollectionModBlocksMixin",
    "environmental.WisteriaTreeFeatureMixin",
    "hominid.HominidClientEventsMixin",
    "jade.JadeDepthFixMixin",
    "minecraft.BedMixin",
    "minecraft.EndCrystalItemMixin",
    "minecraft.EndCrystalMixin",
    "minecraft.ItemStackKeeperMixin",
    "minecraft.PlayerMixin",
    "minecraft.RespawnAnchorMixin",
    "minecraft.SpiderEntityMixin",
    "minecraft.WolfPetArmorMixin",
    "perf.RecipeBookMixin",
    "perf.ReloadableServerResourcesMixin",
    "perf.ServerPlayerMixin",
    "perf.ServerRecipeBookMixin",
    "redstone.DispenserBlockMixin",
    "redstone.PistonBaseBlockMixin",
    "redstone.WaterloggableComparatorMixin",
    "redstone.WaterloggableDiodeMixin",
    "redstone.WaterloggableRepeaterMixin",
    "redstone.caverns_and_chasms.WaterloggableRefractorMixin",
    "redstone.caverns_and_chasms.WaterloggableResistorMixin",
    "redstone.quark.WaterloggableRedstoneRandomizerMixin",
    "tide.TideFishingRodItemMixin",
    "vista.VistaMirrorAlwaysConnectMixin"
  ],
  "client": [
    "minecraft.client.AbstractContainerScreenMixin",
    "minecraft.client.EndCrystalRendererMixin",
    "minecraft.client.ItemPropertiesMixin",
    "minecraft.client.SpiderModelMixin",
    "minecraft.client.WolfArmorLayerMixin",
    "namingunconvention.ModernWorldCreationGameTabMixin",
    "namingunconvention.WorldCreationUiStateMixin",
    "perf.ClientRecipeBookMixin",
    "perf.TagCollectorMixin",
    "snowyspirit.GlowLightParticleMixin",
    "vista.accessor.GameRendererAccessor",
    "vista.accessor.LevelRendererAccessor",
    "vista.VistaCullFrustumFarPlaneMixin",
    "vista.VistaMirrorReflectionDistanceMixin",
    "vista.VistaMirrorThrottleMixin",
    "vista.VistaOffAxisFrustumCacheMixin",
    "vista.VistaSharedStateThrashMixin"
  ],
  "server": [
  ],
  "injectors": {
    "defaultRequire": 1
  },
  "overwrites": {
    "requireAnnotations": true
  }
}